pyplantuml/__init__.py
pyplantuml/core.py
pyplantuml/utils.py
tests/__init__.py
tests/test_core.py
tests/test_utils.py
pythonplantuml-0.2.0.dist-info/LICENSE
pythonplantuml-0.2.0.dist-info/METADATA
pythonplantuml-0.2.0.dist-info/WHEEL
pythonplantuml-0.2.0.dist-info/entry_points.txt
pythonplantuml-0.2.0.dist-info/top_level.txt
pythonplantuml-0.2.0.dist-info/RECORD
