Metadata-Version: 2.1
Name: pythonplantuml
Version: 0.2.0
Summary: A library for generating PlantUML diagrams
Home-page: https://github.com/treezy254/py-plantuml.git
Author: Kamau Samuel
Author-email: gachungasamuel54@gmail.com
Classifier: Development Status :: 3 - Alpha
Classifier: Intended Audience :: Developers
Classifier: License :: OSI Approved :: MIT License
Classifier: Operating System :: OS Independent
Classifier: Programming Language :: Python :: 3
Classifier: Programming Language :: Python :: 3.6
Classifier: Programming Language :: Python :: 3.7
Classifier: Programming Language :: Python :: 3.8
Classifier: Programming Language :: Python :: 3.9
Requires-Python: >=3.6
License-File: LICENSE
Requires-Dist: plantweb
Provides-Extra: dev
Requires-Dist: cairosvg ; extra == 'dev'
Requires-Dist: pytest ; extra == 'dev'
Requires-Dist: sphinx ; extra == 'dev'
